cilib/__init__.py
cilib/cicode1.py
cilib/cicode2.py
cilib/cicode3.py
cilib/cicode4.py
cilib/cicode5.py
cieep_node-0.1.dist-info/METADATA
cieep_node-0.1.dist-info/WHEEL
cieep_node-0.1.dist-info/top_level.txt
cieep_node-0.1.dist-info/RECORD
