Metadata-Version: 2.1
Name: cieep-node
Version: 0.1
Summary: A practical code library
Home-page: UNKNOWN
Author: Your Name
License: UNKNOWN
Platform: UNKNOWN
Classifier: Programming Language :: Python :: 3
Requires-Python: >=3.6
